{
  "ok": true,
  "self": {
    "id": "<%= user[:id] %>",
    "name": "<%= user[:name] %>"
  },
  "team": {
    "id": "<%= team[:id] %>",
    "name": "<%= team[:name] %>"
  },
  "channels": [
  ],
  "ims": [
    {
      "id": "<%= user[:dm_id] %>",
      "is_im": true,
      "user": "<%= user[:id] %>",
      "created": 1458275992,
      "has_pins": false,
      "last_read": "0000000000.000000",
      "latest": null,
      "unread_count": 0,
      "unread_count_display": 0,
      "is_open": true
    }
  ],
  "users": [
    {
      "id": "<%= user[:id] %>",
      "team_id": "<%= team[:id] %>",
      "name": "<%= user[:name] %>",
      "deleted": false,
      "status": null,
      "color": "<%= user[:color] %>",
      "real_name": "<%= user[:real_name] %>",
      "profile": {
        "first_name": "<%= user[:first_name] %>",
        "last_name": "<%= user[:last_name] %>",
        "real_name": "<%= user[:real_name] %>",
        "real_name_normalized": "<%= user[:real_name] %>",
        "email": "<%= user[:email] %>",
        "avatar": "<%= user[:avatar] || '/user_avatar.png' %>"
      },
      "is_admin": false,
      "is_owner": false,
      "is_primary_owner": false,
      "is_restricted": false,
      "is_ultra_restricted": false,
      "is_bot": false,
      "presence": "away"
    }
  ],
  "bots": [
    {
      "id": "herbert-bot-id",
      "team_id": "<%= team[:id] %>",
      "name": "herbert",
      "deleted": false,
      "status": null,
      "color": "2b2b2b",
      "real_name": "Herbert",
      "profile": {
        "first_name": "Herbert",
        "last_name": "",
        "real_name": "Herbert",
        "real_name_normalized": "Herbert",
        "email": "herbert@euston.fish",
        "avatar": "/bot_avatar.png"
      },
      "is_admin": false,
      "is_owner": false,
      "is_primary_owner": false,
      "is_restricted": false,
      "is_ultra_restricted": false,
      "is_bot": true,
      "presence": "away"
    }
  ],
  "url": "<%= team[:url] %>"
}